mongodbconnection_test/__init__.py
mongodbconnection_test/mongo_crud.py
mongodbconnection_test-0.0.8.dist-info/METADATA
mongodbconnection_test-0.0.8.dist-info/WHEEL
mongodbconnection_test-0.0.8.dist-info/top_level.txt
mongodbconnection_test-0.0.8.dist-info/RECORD
